convopus/__init__.py
convopus/app.py
convopus/app_mt.py
convopus/genconf.py
convopus/main.py
ffpb_convopus/__init__.py
ffpb_convopus/ffpb.py
convopus-1.4.2.dist-info/LICENSE
convopus-1.4.2.dist-info/METADATA
convopus-1.4.2.dist-info/WHEEL
convopus-1.4.2.dist-info/entry_points.txt
convopus-1.4.2.dist-info/top_level.txt
convopus-1.4.2.dist-info/RECORD
