Metadata-Version: 2.1
Name: convopus
Version: 1.4.2
Summary: Python CLI program that converts directories of audio files to opus using ffmpeg
Home-page: https://github.com/D221/convopus
Author: D221
Author-email: D221@airmail.cc
License: MIT
Project-URL: Bug Tracker, https://github.com/D221/convopus/issues
Classifier: Programming Language :: Python
Classifier: Programming Language :: Python :: 3
Classifier: Programming Language :: Python :: 3.7
Classifier: Programming Language :: Python :: 3.8
Classifier: Programming Language :: Python :: 3.9
Classifier: Programming Language :: Python :: 3.10
Classifier: Programming Language :: Python :: 3.11
Classifier: Programming Language :: Python :: 3.12
Classifier: License :: OSI Approved :: MIT License
Classifier: Operating System :: OS Independent
Classifier: Operating System :: Microsoft :: Windows
Classifier: Operating System :: POSIX :: Linux
Classifier: Operating System :: MacOS
Classifier: Environment :: Console
Classifier: Topic :: Multimedia
Classifier: Topic :: Multimedia :: Sound/Audio
Classifier: Topic :: Multimedia :: Sound/Audio :: Conversion
Classifier: Topic :: Utilities
License-File: LICENSE
Requires-Dist: tqdm
Requires-Dist: appdirs
